setup.cfg
setup.py
FastPt.egg-info/PKG-INFO
FastPt.egg-info/SOURCES.txt
FastPt.egg-info/dependency_links.txt
FastPt.egg-info/entry_points.txt
FastPt.egg-info/not-zip-safe
FastPt.egg-info/top_level.txt
fastpt/__init__.py
fastpt/compiler.py
fastpt/core.py
fastpt/exceptions.py
fastpt/loader.py
fastpt/runtime.py
fastpt/template.py
fastpt/tests/__init__.py
fastpt/tests/test_basic.py
fastpt/tests/data/__init__.py