Metadata-Version: 1.0
Name: FastPt
Version: 0.1dev
Summary: Really fast well-formed xml templates
Home-page: http://bitbucket.org/rick446/fastpt
Author: Rick Copeland
Author-email: rick446@usa.net
License: MIT
Keywords: template xml
Platform: UNKNOWN
Classifier: Development Status :: 3 - Alpha
Classifier: Environment :: Web Environment
Classifier: Intended Audience :: Developers
Classifier: License :: OSI Approved :: MIT License
Classifier: Topic :: Software Development :: Libraries :: Python Modules
Classifier: Topic :: Text Processing :: Markup :: HTML
Classifier: Topic :: Text Processing :: Markup :: XML
